tests/__init__.py
tests/test_bitcoincash_clients.py
tests/test_bitcoincash_utils.py
xchainpy_bitcoincash/__init__.py
xchainpy_bitcoincash/bitcore_api.py
xchainpy_bitcoincash/client.py
xchainpy_bitcoincash/crypto.py
xchainpy_bitcoincash/haskoin_api.py
xchainpy_bitcoincash/utils.py
xchainpy_bitcoincash/models/__init__.py
xchainpy_bitcoincash/models/api_types.py
xchainpy_bitcoincash/models/client_types.py
xchainpy_bitcoincash-0.2.3.dist-info/LICENSE
xchainpy_bitcoincash-0.2.3.dist-info/METADATA
xchainpy_bitcoincash-0.2.3.dist-info/WHEEL
xchainpy_bitcoincash-0.2.3.dist-info/top_level.txt
xchainpy_bitcoincash-0.2.3.dist-info/RECORD
