Metadata-Version: 2.1
Name: xchainpy-bitcoincash
Version: 0.2.3
Summary: Bitcoincash Module for XChainPy Clients
Home-page: https://github.com/xchainjs/xchainpy-lib/tree/main/xchainpy/xchainpy_bitcoincash
Author: THORChain
Author-email: 
License: MIT
Keywords: THORChain,XChainpy,XChainpy_bitcoincash
Platform: UNKNOWN
Classifier: Intended Audience :: Developers
Classifier: Topic :: Software Development :: Libraries :: Python Modules
Classifier: License :: OSI Approved :: MIT License
Classifier: Programming Language :: Python :: 3
Classifier: Programming Language :: Python :: 3.7
Classifier: Programming Language :: Python :: 3.8
Classifier: Programming Language :: Python
License-File: LICENSE
Requires-Dist: mnemonic (>=0.18)
Requires-Dist: bitcash (>=0.6.1)
Requires-Dist: cashaddress-regtest (>=1.1.0)
Requires-Dist: cashaddress (>=1.0.6)
Requires-Dist: http3 (>=0.6.7)
Requires-Dist: xchainpy-client (>=0.1.6)
Requires-Dist: xchainpy-crypto (>=0.1.11)
Requires-Dist: xchainpy-util (>=0.1.8)
Requires-Dist: bip-utils (==1.11.1)
